<?xml version="1.0" encoding="utf-8"?>
<Entity parent="template_unit_support_trader">
  <Footprint>
    <Circle radius="2.0"/>
    <Height>7.5</Height>
  </Footprint>
  <Identity>
    <Civ>egyptian</Civ>
    <GenericName>Egyptian Merchant</GenericName>
    <SpecificName>šwtj</SpecificName>
    <History>Egypt carried on extensive land trade with other nations, notably in grain exports, and was a center of luxury good exports and imports.</History>
    <Icon>units/celt_support_trader.png</Icon>
    <Tooltip>Trade resources between your own markets and those of your allies.</Tooltip>
  </Identity>
  <Trader>
    <GainMultiplier>1.25</GainMultiplier>
  </Trader>
  <VisualActor>
    <Actor>units/egyptian/support_trader.xml</Actor>
  </VisualActor>
</Entity>
